README.md
setup.py
flask_validation/__init__.py
flask_validation/common_regex.py
flask_validation/decorators.py
flask_validation/fields.py
flask_validation/validator.py
flask_validation.egg-info/PKG-INFO
flask_validation.egg-info/SOURCES.txt
flask_validation.egg-info/dependency_links.txt
flask_validation.egg-info/requires.txt
flask_validation.egg-info/top_level.txt