Metadata-Version: 1.2
Name: flask-validation
Version: 1.0.2
Summary: A Pythonic way for validate requested JSON payload of Flask
Home-page: https://github.com/JoMingyu/Flask-Validation
Author: PlanB
Author-email: mingyu.planb@gmail.com
Maintainer: PlanB
Maintainer-email: mingyu.planb@gmail.com
License: Apache License 2.0
Platform: UNKNOWN
Classifier: Programming Language :: Python
Classifier: Programming Language :: Python :: 3
Classifier: Topic :: Software Development :: Libraries :: Python Modules
